crispy_forms_materialize/__init__.py
crispy_forms_materialize/layout.py
crispy_forms_materialize/models.py
crispy_forms_materialize/templates/materialize_css_forms/betterform.html
crispy_forms_materialize/templates/materialize_css_forms/display_form.html
crispy_forms_materialize/templates/materialize_css_forms/errors.html
crispy_forms_materialize/templates/materialize_css_forms/errors_formset.html
crispy_forms_materialize/templates/materialize_css_forms/field.file.html
crispy_forms_materialize/templates/materialize_css_forms/field.html
crispy_forms_materialize/templates/materialize_css_forms/field.strict.html
crispy_forms_materialize/templates/materialize_css_forms/inline_switch.html
crispy_forms_materialize/templates/materialize_css_forms/multifield.html
crispy_forms_materialize/templates/materialize_css_forms/switch.html
crispy_forms_materialize/templates/materialize_css_forms/uni_form.html
crispy_forms_materialize/templates/materialize_css_forms/uni_formset.html
crispy_forms_materialize/templates/materialize_css_forms/whole_uni_form.html
crispy_forms_materialize/templates/materialize_css_forms/whole_uni_formset.html
crispy_forms_materialize/templates/materialize_css_forms/layout/baseinput.html
crispy_forms_materialize/templates/materialize_css_forms/layout/buttongroup.html
crispy_forms_materialize/templates/materialize_css_forms/layout/buttonholder.html
crispy_forms_materialize/templates/materialize_css_forms/layout/checkboxselectmultiple.html
crispy_forms_materialize/templates/materialize_css_forms/layout/div.html
crispy_forms_materialize/templates/materialize_css_forms/layout/inline_field.html
crispy_forms_materialize/templates/materialize_css_forms/layout/multifield.html
crispy_forms_materialize/templates/materialize_css_forms/layout/splitdatetime_field.html
crispy_forms_materialize-0.1.dist-info/DESCRIPTION.rst
crispy_forms_materialize-0.1.dist-info/METADATA
crispy_forms_materialize-0.1.dist-info/RECORD
crispy_forms_materialize-0.1.dist-info/WHEEL
crispy_forms_materialize-0.1.dist-info/metadata.json
crispy_forms_materialize-0.1.dist-info/top_level.txt
