Metadata-Version: 1.1
Name: crispy-forms-materialize
Version: 0.1
Summary: 
